cwordtm/__init__.py
cwordtm/meta.py
cwordtm/pivot.py
cwordtm/quot.py
cwordtm/ta.py
cwordtm/tm.py
cwordtm/util.py
cwordtm/version.py
cwordtm/viz.py
cwordtm/data/Book Category.xlsx
cwordtm/data/bible_vocab.txt
cwordtm/data/book_cat.csv
cwordtm/data/book_categories.csv
cwordtm/data/book_no.csv
cwordtm/data/category.csv
cwordtm/data/category_chi.csv
cwordtm/data/cuv.csv
cwordtm/data/msyh.ttc
cwordtm/data/tc_stopwords_2.txt
cwordtm/data/user_dict_4.txt
cwordtm/data/web.csv
cwordtm/dictionary/dict.txt.big.txt
cwordtm/dictionary/stopWord_cloud.txt
cwordtm/dictionary/stopWord_cloudmod.txt
cwordtm/dictionary/stopWord_summar.txt
cwordtm/dictionary/stopWord_union.txt
cwordtm/dictionary/userdict.txt
cwordtm/images/arrow.jpg
cwordtm/images/disc.jpg
cwordtm/images/heart.jpg
cwordtm/images/triangle.jpg
cwordtm-0.7.7.dist-info/LICENSE.txt
cwordtm-0.7.7.dist-info/METADATA
cwordtm-0.7.7.dist-info/WHEEL
cwordtm-0.7.7.dist-info/top_level.txt
cwordtm-0.7.7.dist-info/RECORD
