Metadata-Version: 2.1
Name: cwordtm
Version: 0.7.7
Summary: CWordTM: Towards a Topic Modeling Toolkit from Low-Code to Pro-Code
Author: Dr. Johnny CHENG
Author-email: <drjohnnycheng@gmail.com>
Project-URL: Documentation, https://cwordtm.readthedocs.io
Project-URL: GitHub Repository, https://github.com/drjohnnycheng/cwordtm
Keywords: topic modeling,BERTopic,LDA,NMF,NLP,Holy Bible,Chinese text preprocessing,pre-packaging,low-code,pro-code,meta programming,CWordTM
Classifier: Intended Audience :: Developers
Classifier: Intended Audience :: Education
Classifier: Intended Audience :: Information Technology
Classifier: Intended Audience :: Religion
Classifier: Intended Audience :: Science/Research
Classifier: Programming Language :: Python :: 3.10
Classifier: Operating System :: OS Independent
License-File: LICENSE.txt
Requires-Dist: numpy
Requires-Dist: pandas
Requires-Dist: importlib-resources
Requires-Dist: regex
Requires-Dist: nltk
Requires-Dist: matplotlib
Requires-Dist: wordcloud
Requires-Dist: pillow
Requires-Dist: jieba
Requires-Dist: gensim
Requires-Dist: pyLDAvis
Requires-Dist: bertopic
Requires-Dist: transformers
Requires-Dist: spacy
Requires-Dist: seaborn
Requires-Dist: wikipedia
Requires-Dist: scipy
Requires-Dist: importlib
Requires-Dist: networkx
Requires-Dist: plotly
Requires-Dist: IPython
Requires-Dist: scikit-learn
Requires-Dist: torch
Requires-Dist: sentencepiece
